{
  "products": {
    "new":[
        {
            "type":"new",
            "id":11309,
            "isActiveHeart":false,
            "isActiveCart":false,
            "title":"pants bell bottoms",
            "price":170,
            "color":[{"colorName":"black","colorHEX":"#252525"}],
            "composition":[{"property":"viscose","value":"58%"},{"property":"nylon","value":"32%"},{"property":"lycra","value":"10%"}],
            "description":"Ideal for height 165-175 cm, after the first wash it may shrink 3-5 cm. The zipper is on the back."
        },
        {
            "type":"new",
            "id":93214,
            "isActiveHeart":false,
            "isActiveCart":false,
            "title":"shirt milk",
            "price":175,
            "color":[{"colorName":"white","colorHEX":"#E2E2E0"}],
            "composition":[{"property":"cotton","value":"98%"},{"property":"elastane","value":"2%"}],
            "description":"Soft cotton shirt. Made in one size. Oversize cut."
        },
        {
            "type":"new",
            "id":73949,
            "isActiveHeart":false,
            "isActiveCart":false,
            "title":"jacket with fringe",
            "price":290,"color":[{"colorName":"black","colorHEX":"#252525"}],
            "composition":[{"property":"polyester","value":"75%"},{"property":"viscose","value":"21%"},{"property":"spandex","value":"4%"}],
            "description":"Goes well with pants bell bottoms."
        },
        {
            "type":"new",
            "id":18869,
            "isActiveHeart":false,
            "isActiveCart":false,
            "title":"top heart",
            "price":140,
            "color":[{"colorName":"black","colorHEX":"#252525"},{"colorName":"white","colorHEX":"#E2E2E0"}],
            "composition":[{"property":"polyester","value":"95%"},{"property":"elastane","value":"5%"}],
            "description":"Straps are not removable, with locks. Pleasant to the body soft satin fabric. Doesn't shine through."
        },
        {
            "type":"new",
            "id":67023,
            "isActiveHeart":false,
            "isActiveCart":false,
            "title":"top shells",
            "price":180,
            "color":[{"colorName":"black","colorHEX":"#252525"}],
            "composition":[{"property":"polyester","value":"95%"},{"property":"elastane","value":"5%"}],
            "description":"Straps are not removable, with locks. Pleasant to the body soft satin fabric. Doesn't shine through."
        },
        {
            "type":"new",
            "id":43289,
            "isActiveHeart":false,
            "isActiveCart":false,
            "title":"top with flounces",
            "price":130,
            "color":[{"colorName":"white","colorHEX":"#E2E2E0"}],
            "composition":[{"property":"cotton","value":"97%"},{"property":"elastane","value":"3%"}]
        },
        {
            "type":"new",
            "id":24299,
            "isActiveHeart":false,
            "isActiveCart":false,
            "title":"skirt tweed",
            "price":120,
            "color":[{"colorName":"black","colorHEX":"#252525"}],
            "composition":[{"property":"polyester","value":"60%"},{"property":"viscose","value":"37%"},{"property":"elastane","value":"3%"}],
            "description":"The product is lined."
        },
        {
            "type":"new",
            "id":36679,
            "isActiveHeart":false,
            "isActiveCart":false,
            "title":"shirt sequins",
            "price":185,
            "color":[{"colorName":"black","colorHEX":"#252525"},{"colorName":"biege","colorHEX":"#E8D3B9"}],
            "composition":[{"property":"polyester","value":"95%"},{"property":"elastane","value":"5%"}]
        },
        {
            "type":"new",
            "id":11099,
            "isActiveHeart":false,
            "isActiveCart":false,
            "title":"jacket tweed",
            "price":230,
            "color":[{"colorName":"black","colorHEX":"#252525"}],
            "composition":[{"property":"polyester","value":"60%"},{"property":"viscose","value":"37%"},{"property":"elastane","value":"3%"}]
        },
        {
            "type":"new",
            "id":391,
            "isActiveHeart":false,
            "isActiveCart":false,
            "title":"cardigan long",
            "price":390,"color":[{"colorName":"white","colorHEX":"#E2E2E0"}],
            "composition":[{"property":"acrylic fabrics","value":"70%"},{"property":"wool","value":"30%"}],
            "description":"The cardigan isn't prickly, very warm and pleasant to the body."
        },
        {
            "type":"new",
            "id":29169,
            "isActiveHeart":false,
            "isActiveCart":false,
            "title":"shirt graphite",
            "price":150,
            "color":[{"colorName":"graphite","colorHEX":"#66676A"}],
            "composition":[{"property":"viscose","value":"97%"},{"property":"elastane","value":"3%"}]
        },
        {
            "type":"new",
            "id":19907,
            "isActiveHeart":false,
            "isActiveCart":false,
            "title":"cropped top with buttons",
            "price":140,
            "color":[{"colorName":"white","colorHEX":"#E2E2E0"}],
            "composition":[{"property":"cotton","value":"97%"},{"property":"elastane","value":"3%"}],
            "description":"The top is made of cotton fabric, fits snugly to the body."
        }
    ],

    "bodysuits":[
        {
            "type":"bodysuits",
            "id":87690,
            "isActiveHeart":false,
            "isActiveCart":false,
            "title":"with assembly",
            "price":185,
            "color":[{"colorName":"cream","colorHEX":"#F6E8B1"}],
            "composition":[{"property":"cotton","value":"97%"},{"property":"elastane","value":"3%"}],
            "description":"Long sleeve bodysuit in double cotton fabric. The fabric is not translucent, soft, stretches well. The product is made in the form of a thong."
        },
        {
            "type":"bodysuits",
            "id":90251,
            "isActiveHeart":false,
            "isActiveCart":false,
            "title":"with lock",
            "price":185,
            "color":[{"colorName":"black","colorHEX":"#252525"}],
            "composition":[{"property":"cotton","value":"97%"},{"property":"elastane","value":"3%"}],
            "description":"Clasp at the bottom. Accessories to match the bodysuit."
        },
        {
            "type":"bodysuits",
            "id":71655,
            "isActiveHeart":false,
            "isActiveCart":false,
            "title":"knitted with long sleeve",
            "price":190,
            "color":[{"colorName":"biege","colorHEX":"#E8D3B9"}],
            "composition":[{"property":"viscose","value":"97%"},{"property":"elastane","value":"3%"}],
            "description":"Clasp at the bottom. Stretches well and fits all sizes."
        },
        {
            "type":"bodysuits",
            "id":6484,
            "isActiveHeart":false,
            "isActiveCart":false,
            "title":"basic",
            "price":180,
            "color":[{"colorName":"graphite","colorHEX":"#66676A"},{"colorName":"latte","colorHEX":"#DEC7AD"}],
            "composition":[{"property":"cotton","value":"97%"},{"property":"elastane","value":"3%"}],
            "description":"Long sleeve bodysuit in double cotton fabric. The fabric is not translucent, soft, stretches well. The product is made in the form of a thong."
        },
        {
            "type":"bodysuits",
            "id":88023,
            "isActiveHeart":false,
            "isActiveCart":false,
            "title":"with round neckline",
            "price":185,
            "color":[{"colorName":"heavenly","colorHEX":"#C5DFFB"},{"colorName":"cappuccino","colorHEX":"#C5AB9F"},{"colorName":"pink","colorHEX":"#FADADD"},{"colorName":"black","colorHEX":"#252525"}],
            "composition":[{"property":"cotton","value":"97%"},{"property":"elastane","value":"3%"}],
            "description":"Clasp at the bottom. Accessories to match the bodysuit."
        }
    ],
    
    "costumes":[
        {
            "type":"costumes",
            "id":48077,
            "isActiveHeart":false,
            "isActiveCart":false,
            "title":"silk",
            "price":270,
            "color":[{"colorName":"black","colorHEX":"#252525"}],
            "composition":[{"property":"viscose","value":"65%"},{"property":"cotton","value":"30%"},{"property":"elastane","value":"5%"}]
        },
        {
            "type":"costumes",
            "id":79143,
            "isActiveHeart":false,
            "isActiveCart":false,
            "title":"knitted",
            "price":230,
            "color":[{"colorName":"lavender","colorHEX":"#DEACF3"}],
            "composition":[{"property":"viscose","value":"97%"},{"property":"elastane","value":"3%"}]
        },
        {
            "type":"costumes",
            "id":563,
            "isActiveHeart":false,
            "isActiveCart":false,
            "title":"summer",
            "price":190,
            "color":[{"colorName":"heavenly","colorHEX":"#C5DFFB"}],
            "composition":[{"property":"cotton","value":"92%"},{"property":"lycra","value":"8%"}]
        },
        {
            "type":"costumes",
            "id":84092,
            "isActiveHeart":false,
            "isActiveCart":false,
            "title":"with flounces",
            "price":270,
            "color":[{"colorName":"graphite","colorHEX":"#66676A"}],
            "composition":[{"property":"cotton","value":"50%"},{"property":"acrylic fabrics","value":"50%"}],
            "description":"Flounces aren't removable. After washing they perfectly retain their shape."
        },
        {
            "type":"costumes",
            "id":41203,
            "isActiveHeart":false,
            "isActiveCart":false,
            "title":"insulated with lock",
            "price":320,
            "color":[{"colorName":"graphite","colorHEX":"#66676A"}],
            "composition":[{"property":"cotton","value":"65%"},{"property":"polyester","value":"35%"}],
            "description":"The product is made with insulation from the footer. Suitable for height 160-170, 170-180."
        }
    ],
    
    "dresses":[
        {
            "type":"dresses",
            "id":26960,
            "isActiveHeart":false,
            "isActiveCart":false,
            "title":"knitted with cutout",
            "price":260,
            "color":[{"colorName":"biege","colorHEX":"#E8D3B9"}],
            "composition":[{"property":"viscose","value":"96%"},{"property":"elastane","value":"4%"}],
            "description":"Basic dress. Slim fit silhouette perfectly emprasister the figure. Thanks to artificial fibers, the material doesn't wrinkle and retains its shape."
        },
        {
            "type":"dresses",
            "id":44033,
            "isActiveHeart":false,
            "isActiveCart":false,
            "title":"with blue flowers",
            "price":210,
            "color":[{"colorName":"white","colorHEX":"#E2E2E0"}],
            "composition":[{"property":"linen","value":"55%"},{"property":"viscose","value":"45%"}]
        },
        {
            "type":"dresses",
            "id":20070,
            "isActiveHeart":false,
            "isActiveCart":false,
            "title":"velvet",
            "price":135,
            "color":[{"colorName":"black","colorHEX":"#252525"}],
            "composition":[{"property":"polyester","value":"95%"},{"property":"elastane","value":"5%"}]
        },
        {
            "type":"dresses",
            "id":20071,
            "isActiveHeart":false,
            "isActiveCart":false,
            "title":"velvet first clone",
            "price":145,
            "color":[{"colorName":"black","colorHEX":"#252525"}],
            "composition":[{"property":"polyester","value":"95%"},{"property":"elastane","value":"5%"}]
        },
        {
            "type":"dresses",
            "id":20072,
            "isActiveHeart":false,
            "isActiveCart":false,
            "title":"velvet second clone",
            "price":155,
            "color":[{"colorName":"black","colorHEX":"#252525"}],
            "composition":[{"property":"polyester","value":"95%"},{"property":"elastane","value":"5%"}]
        },
        {
            "type":"dresses",
            "id":20073,
            "isActiveHeart":false,
            "isActiveCart":false,
            "title":"velvet third clone",
            "price":165,
            "color":[{"colorName":"black","colorHEX":"#252525"}],
            "composition":[{"property":"polyester","value":"95%"},{"property":"elastane","value":"5%"}]
        },
        {
            "type":"dresses",
            "id":20074,
            "isActiveHeart":false,
            "isActiveCart":false,
            "title":"velvet fourth clone",
            "price":175,
            "color":[{"colorName":"black","colorHEX":"#252525"}],
            "composition":[{"property":"polyester","value":"95%"},{"property":"elastane","value":"5%"}]
        },
        {
            "type":"dresses",
            "id":20075,
            "isActiveHeart":false,
            "isActiveCart":false,
            "title":"velvet fifth clone",
            "price":185,
            "color":[{"colorName":"black","colorHEX":"#252525"}],
            "composition":[{"property":"polyester","value":"95%"},{"property":"elastane","value":"5%"}]
        }
    ],
    
    "shirts":[
        {
            "type":"shirts",
            "id":63753,
            "isActiveHeart":false,
            "isActiveCart":false,
            "title":"in checker",
            "price":126,
            "color":[{"colorName":"biege","colorHEX":"#E8D3B9"}],
            "composition":[{"property":"polyester","value":"95%"},{"property":"elastane","value":"5%"}]
        },
        {
            "type":"shirts",
            "id":94573,
            "isActiveHeart":false,
            "isActiveCart":false,
            "title":"classic",
            "price":185,
            "color":[{"colorName":"milky","colorHEX":"#FDF6E4"},{"colorName":"heavenly","colorHEX":"#C5DFFB"}],
            "composition":[{"property":"polyester","value":"65%"},{"property":"viscose","value":"45%"},{"property":"elastane","value":"5%"}]
        },
        {
            "type":"shirts",
            "id":35200,
            "isActiveHeart":false,
            "isActiveCart":false,
            "title":"silk",
            "price":135,
            "color":[{"colorName":"milky","colorHEX":"#FDF6E4"}],
            "composition":[{"property":"viscose","value":"97%"},{"property":"elastane","value":"3%"}],
            "description":"The shirt is made of light silk material, ideal for warm weather."
        },
        {
            "type":"shirts",
            "id":75624,"isActiveHeart":false,
            "isActiveCart":false,
            "title":"warm",
            "price":270,
            "color":[{"colorName":"white","colorHEX":"#E2E2E0"},{"colorName":"cappuccino","colorHEX":"#C5AB9F"},{"colorName":"black","colorHEX":"#252525"}],
            "composition":[{"property":"polyester","value":"65%"},{"property":"viscose","value":"30%"},{"property":"elastane","value":"5%"}],
            "description":"The shirt is made of dense soft material, ideal for cool weather. Oversize cut."
        },
        {
            "type":"shirts",
            "id":62577,
            "isActiveHeart":false,
            "isActiveCart":false,
            "title":"night",
            "price":150,
            "color":[{"colorName":"blue steel","colorHEX":"#B0C4DE"}],
            "composition":[{"property":"viscose","value":"97%"},{"property":"elastane","value":"3%"}],
            "description":"The shirt is made of light silk material, ideal for warm weather."
        }
    ],
    
    "skirts":[
        {
            "type":"skirts",
            "id":1277,
            "isActiveHeart":false,
            "isActiveCart":false,
            "title":"plisse",
            "price":200,
            "color":[{"colorName":"biege","colorHEX":"#E8D3B9"}],
            "composition":[{"property":"viscose","value":"97%"},{"property":"elastane","value":"3%"}]
        },
        {
            "type":"skirts",
            "id":41206,
            "isActiveHeart":false,
            "isActiveCart":false,
            "title":"leather long",
            "price":210,
            "color":[{"colorName":"black","colorHEX":"#252525"}],
            "composition":[{"property":"polyester","value":"50%"},{"property":"polyurethane","value":"50%"}],
            "description":"Suitable for height from 155 cm to 180 cm."
        },
        {
            "type":"skirts",
            "id":74843,
            "isActiveHeart":false,
            "isActiveCart":false,
            "title":"silk",
            "price":159,
            "color":[{"colorName":"emerald","colorHEX":"#008080"}],
            "composition":[{"property":"viscose","value":"97%"},{"property":"elastane","value":"3%"}]
        },
        {
            "type":"skirts",
            "id":74844,
            "isActiveHeart":false,
            "isActiveCart":false,
            "title":"silk first clone",
            "price":161,
            "color":[{"colorName":"emerald","colorHEX":"#008080"}],
            "composition":[{"property":"viscose","value":"97%"},{"property":"elastane","value":"3%"}]
        },
        {
            "type":"skirts",
            "id":74845,
            "isActiveHeart":false,
            "isActiveCart":false,
            "title":"silk second clone",
            "price":162,
            "color":[{"colorName":"emerald","colorHEX":"#008080"}],
            "composition":[{"property":"viscose","value":"97%"},{"property":"elastane","value":"3%"}]
        },
        {
            "type":"skirts",
            "id":74846,
            "isActiveHeart":false,
            "isActiveCart":false,
            "title":"silk third clone",
            "price":163,
            "color":[{"colorName":"emerald","colorHEX":"#008080"}],
            "composition":[{"property":"viscose","value":"97%"},{"property":"elastane","value":"3%"}]
        },
        {
            "type":"skirts",
            "id":74847,
            "isActiveHeart":false,
            "isActiveCart":false,
            "title":"silk fourth clone",
            "price":164,
            "color":[{"colorName":"emerald","colorHEX":"#008080"}],
            "composition":[{"property":"viscose","value":"97%"},{"property":"elastane","value":"3%"}]
        },
        {
            "type":"skirts",
            "id":74848,
            "isActiveHeart":false,
            "isActiveCart":false,
            "title":"silk fifth clone",
            "price":165,
            "color":[{"colorName":"emerald","colorHEX":"#008080"}],
            "composition":[{"property":"viscose","value":"97%"},{"property":"elastane","value":"3%"}]
        }
    ],
    
    "sweaters":[
        {
            "type":"sweaters",
            "id":89063,
            "isActiveHeart":false,
            "isActiveCart":false,
            "title":"ginger cookiet",
            "price":250,
            "color":[{"colorName":"red","colorHEX":"#DC1C13"}],
            "composition":[{"property":"acrylic fabrics","value":"70%"},{"property":"wool","value":"30%"}],
            "description":"Back length - 75 cm, width - 60 cm"
        },
        {
            "type":"sweaters",
            "id":91597,
            "isActiveHeart":false,
            "isActiveCart":false,
            "title":"olof",
            "price":250,
            "color":[{"colorName":"blue","colorHEX":"#90CBF9"}],
            "composition":[{"property":"acrylic fabrics","value":"70%"},{"property":"wool","value":"30%"}],
            "description":"Back length - 75 cm, width - 60 cm"
        },
        {
            "type":"sweaters",
            "id":11595,
            "isActiveHeart":false,
            "isActiveCart":false,
            "title":"cheburashka",
            "price":250,
            "color":[{"colorName":"orange","colorHEX":"#E56717"}],
            "composition":[{"property":"acrylic fabrics","value":"70%"},{"property":"wool","value":"30%"}],
            "description":"Back length - 75 cm, width - 60 cm"
        },
        {
            "type":"sweaters",
            "id":93270,
            "isActiveHeart":false,
            "isActiveCart":false,
            "title":"honeycombs",
            "price":270,
            "color":[{"colorName":"grape/lavender","colorHEX":"#931f80"}],
            "composition":[{"property":"acrylic fabrics","value":"50%"},{"property":"cotton","value":"50%"}],
            "description":"Reversible sweater. You get a sweater 2 in 1: one side is dark grape, the other is light lavender."
        },
        {
            "type":"sweaters",
            "id":9343,
            "isActiveHeart":false,
            "isActiveCart":false,
            "title":"with slits on the sides",
            "price":190,
            "color":[{"colorName":"lime","colorHEX":"#C2F70F"}],
            "composition":[{"property":"acrylic fabrics","value":"50%"},{"property":"cotton","value":"50%"}],
            "description":"Suitable for height: from 155 cm to 180 cm. Oversize cut. Suitable for sizes 42-48."
        },
        {
            "type":"sweaters",
            "id":41662,
            "isActiveHeart":false,
            "isActiveCart":false,
            "title":"with holes",
            "price":290,
            "color":[{"colorName":"biege","colorHEX":"#E8D3B9"}],
            "composition":[{"property":"acrylic fabrics","value":"50%"},{"property":"cotton","value":"50%"}],
            "description":"Suitable for height: from 155 cm to 180 cm. Oversize cut. Suitable for sizes 42-48."
        },
        {
            "type":"sweaters",
            "id":17301,
            "isActiveHeart":false,
            "isActiveCart":false,
            "title":"striped",
            "price":230,
            "color":[{"colorName":"black","colorHEX":"#252525"},{"colorName":"pink","colorHEX":"#FFC0CB"}],
            "composition":[{"property":"acrylic fabrics","value":"70%"},{"property":"wool","value":"30%"}],
            "description":"The sweater is made from high-volume wool yarn. Soft, not heavy, slightly tingly and, like all woolen products, tends to have minimal pilling."
        },
        {
            "type":"sweaters",
            "id":60451,
            "isActiveHeart":false,
            "isActiveCart":false,
            "title":"euphoria",
            "price":260,
            "color":[{"colorName":"green","colorHEX":"#28713E"}],
            "composition":[{"property":"acrylic fabrics","value":"50%"},{"property":"cotton","value":"50%"}],
            "description":"Suitable for height: from 155 cm to 180 cm. Oversize cut. Suitable for sizes 42-48."
        }
    ]
}
}